nicewoo/__init__.py
nicewoo/keywords.py
nicewoo/language.py
nicewoo/stopwords.py
nicewoo/summarizer.py
nicewoo-0.1.0.dist-info/licenses/LICENSE
nicewoo-0.1.0.dist-info/METADATA
nicewoo-0.1.0.dist-info/WHEEL
nicewoo-0.1.0.dist-info/top_level.txt
nicewoo-0.1.0.dist-info/RECORD
